microkit
