Metadata-Version: 1.1
Name: microkit
Version: 0.3
Summary: A helper kit to power the APIs
Home-page: https://github.com/innovaccer/microkit
Author: Ayush Aggarwal
Author-email: ayushaggarwal.97@gmail.com
License: GNU General Public License
Download-URL: https://github.com/innovaccer/microkit/archive/V1.0.tar.gz
Keywords: python,flask,response,logger
Platform: UNKNOWN
Classifier: Development Status :: 3 - Alpha
Classifier: Intended Audience :: Developers
Classifier: Topic :: Software Development :: Build Tools
Classifier: Programming Language :: Python :: 2.7
